pylib/__init__.py
pylib/blob.py
pylib/id.py
pylib/optional.py
pylib/resource.py
pylib/string.py
pylib/tem/__init__.py
pylib/tem/fileloader.py
pylib/tem/manager.py
spaceport/__init__.py
spaceport/globals.py
spaceport/llm.py
spaceport/logging.py
spaceport/op/__init__.py
spaceport/op/browser.py
spaceport/op/fs.py
spaceport/op/gui.py
spaceport/op/repl.py
spaceport/op/sdoc.py
spaceport/op/table.py
spaceport/op/target.py
spaceport/speccer/__init__.py
spaceport/speccer/_langchain_text_splitter.py
spaceport/speccer/arranger.py
spaceport/speccer/knowledge.py
spaceport/speccer/op_docs.py
spaceport/speccer/rewriter.py
spaceport/speccer/transpiler.py
spaceport/subject/__init__.py
spaceport/subject/factory.py
spaceport/subject/impl_pkg.py
spaceport/tpyi/__init__.py
spaceport/tpyi/errors.py
spaceport/tpyi/exec.py
spaceport/tpyi/resolver.py
spaceport/workspace/__init__.py
spaceport/workspace/_fetch.py
spaceport/workspace/_filenames.py
spaceport/workspace/_yaml.py
spaceport/workspace/artifact.py
spaceport/workspace/env.py
spaceport/workspace/manifest.py
spaceport/workspace/workspace.py
spaceport_cli/__init__.py
spaceport_cli/_util.py
spaceport_cli/env.py
spaceport_cli/main.py
spaceport_cli/test.py
spaceport_cli/toolchain.py
spaceport_cli/transpile.py
spaceport_cli/workspace.py
spaceport_simpl/__init__.py
spaceport_simpl/browser.py
spaceport_simpl/container.py
spaceport_simpl/dummy.py
spaceport_simpl/fs.py
spaceport_simpl/repl.py
spaceport_simpl/sdoc.py
tests/__init__.py
tests/test_globals.py
tests/test_speccer.py
tests/test_tpyi.py
tests/simpl/__init__.py
tests/simpl/test_fs.py
tests/simpl/test_repl.py
tests/simpl/test_sdoc.py
tests/workspace/__init__.py
tests/workspace/test_artifact.py
tests/workspace/test_env.py
tests/workspace/test_workspace.py
spaceport-0.1.6.dist-info/LICENSE
spaceport-0.1.6.dist-info/METADATA
spaceport-0.1.6.dist-info/WHEEL
spaceport-0.1.6.dist-info/entry_points.txt
spaceport-0.1.6.dist-info/top_level.txt
spaceport-0.1.6.dist-info/RECORD
