Metadata-Version: 2.1
Name: spaceport
Version: 0.1.6
Summary: Spaceport executes specs as test code
Author-email: Elementary Dev <dev@elem.app>
License:                                  Apache License
Project-URL: GitHub, https://github.com/elem-app/spaceport
Requires-Python: >=3.12
License-File: LICENSE
Requires-Dist: aiofiles>=24.1.0
Requires-Dist: anthropic>=0.41.0
Requires-Dist: click>=8.1.7
Requires-Dist: jinja2>=3.1.4
Requires-Dist: numpy>=2.2.0
Requires-Dist: openai>=1.57.0
Requires-Dist: packaging>=24.2
Requires-Dist: pydantic>=2.10.3
Requires-Dist: python-dotenv>=1.0.1
Requires-Dist: ruamel-yaml>=0.18.6
